kantanoidc/__init__.py
kantanoidc/apps.py
kantanoidc/client.py
kantanoidc/errors.py
kantanoidc/urls.py
kantanoidc/views.py
djangokantanoidc-0.1.6.dist-info/LICENSE
djangokantanoidc-0.1.6.dist-info/METADATA
djangokantanoidc-0.1.6.dist-info/WHEEL
djangokantanoidc-0.1.6.dist-info/top_level.txt
djangokantanoidc-0.1.6.dist-info/RECORD
