Metadata-Version: 2.1
Name: djangokantanoidc
Version: 0.1.6
Summary: Helper app as oidc client
Home-page: https://github.com/mmiyajima2/django-kantanoidc
Author: Masafumi Miyajima
Author-email: mmiyajima2@gmail.com
License: MIT
Keywords: django oidc
Platform: UNKNOWN
Classifier: Environment :: Web Environment
Classifier: Framework :: Django :: 2.0
Classifier: Framework :: Django :: 2.1
Classifier: License :: OSI Approved :: MIT License
Classifier: Programming Language :: Python :: 3.6
Classifier: Programming Language :: Python :: 3.7
Requires-Dist: django
Requires-Dist: requests
Requires-Dist: urllib3 (>=1.24.2)
